Ej2/rom.v

module rom (add, lo, Lect, ce);
input [7:0] add;
output [7:0] lo;
input Lect;
input ce;


reg [7:0]    mem [0:3999] ;
integer file_pointer;

assign lo = (ce && Lect) ? mem[add] : 8'b0;

integer x;

initial begin
  $readmemb("Ej2.list",mem);
end


endmodule

Ej2/rom_tb.v
module rom_tb;
 reg [7:0] add;
 reg Lect, ce;
 wire [7:0] lo;
 integer x;

 initial begin
   add = 0;
   Lect = 0;
   ce      = 0;
   #10 $display ("Valor entrada | Valor cargado | Lectura activada | Chip activado | iteración");
      $monitor("%b | %b | %b | %b | %d", add, lo, Lect, ce, x);

   for (x = 0; x <3999; x = x +1 )begin
     #5 add = x;
     Lect = 1;
     ce = 1;
     #5 Lect = 0;
     ce = 0;
     add = 0;
   end
 end

rom U(add, lo, Lect,ce);

initial
  #500000 $finish;
initial begin
  $dumpfile("rom_tb.vcd");
  $dumpvars(0, rom_tb);
end

endmodule

Ej2/rom_tb.vcd
$date
	Sat Oct 24 19:29:50 2020
$end
$version
	Icarus Verilog
$end
$timescale
	1ps
$end
$scope module rom_tb $end
$var wire 8 ! lo [7:0] $end
$var reg 1 " Lect $end
$var reg 8 # add [7:0] $end
$var reg 1 $ ce $end
$var integer 32 % x [31:0] $end
$scope module U $end
$var wire 1 " Lect $end
$var wire 8 & add [7:0] $end
$var wire 1 $ ce $end
$var wire 8 ' lo [7:0] $end
$upscope $end
$upscope $end
$enddefinitions $end
#0
$dumpvars
b0 '
b0 &
bx %
0$
b0 #
0"
b0 !
$end
#10
b0 %
#15
b1 !
b1 '
1$
1"
#20
b0 !
b0 '
b1 %
0$
0"
#25
b10 !
b10 '
1$
1"
b1 #
b1 &
#30
b0 !
b0 '
b10 %
b0 #
b0 &
0$
0"
#35
b11 !
b11 '
1$
1"
b10 #
b10 &
#40
b0 !
b0 '
b11 %
b0 #
b0 &
0$
0"
#45
b100 !
b100 '
1$
1"
b11 #
b11 &
#50
b0 !
b0 '
b100 %
b0 #
b0 &
0$
0"
#55
b101 !
b101 '
1$
1"
b100 #
b100 &
#60
b0 !
b0 '
b101 %
b0 #
b0 &
0$
0"
#65
b110 !
b110 '
1$
1"
b101 #
b101 &
#70
b0 !
b0 '
b110 %
b0 #
b0 &
0$
0"
#75
b111 !
b111 '
1$
1"
b110 #
b110 &
#80
b0 !
b0 '
b111 %
b0 #
b0 &
0$
0"
#85
b1000 !
b1000 '
1$
1"
b111 #
b111 &
#90
b0 !
b0 '
b1000 %
b0 #
b0 &
0$
0"
#95
b1001 !
b1001 '
1$
1"
b1000 #
b1000 &
#100
b0 !
b0 '
b1001 %
b0 #
b0 &
0$
0"
#105
b1010 !
b1010 '
1$
1"
b1001 #
b1001 &
#110
b0 !
b0 '
b1010 %
b0 #
b0 &
0$
0"
#115
b1011 !
b1011 '
1$
1"
b1010 #
b1010 &
#120
b0 !
b0 '
b1011 %
b0 #
b0 &
0$
0"
#125
b1100 !
b1100 '
1$
1"
b1011 #
b1011 &
#130
b0 !
b0 '
b1100 %
b0 #
b0 &
0$
0"
#135
b1101 !
b1101 '
1$
1"
b1100 #
b1100 &
#140
b0 !
b0 '
b1101 %
b0 #
b0 &
0$
0"
#145
b1110 !
b1110 '
1$
1"
b1101 #
b1101 &
#150
b0 !
b0 '
b1110 %
b0 #
b0 &
0$
0"
#155
b1111 !
b1111 '
1$
1"
b1110 #
b1110 &
#160
b0 !
b0 '
b1111 %
b0 #
b0 &
0$
0"
#165
b10000 !
b10000 '
1$
1"
b1111 #
b1111 &
#170
b0 !
b0 '
b10000 %
b0 #
b0 &
0$
0"
#175
b10001 !
b10001 '
1$
1"
b10000 #
b10000 &
#180
b0 !
b0 '
b10001 %
b0 #
b0 &
0$
0"
#185
b10010 !
b10010 '
1$
1"
b10001 #
b10001 &
#190
b0 !
b0 '
b10010 %
b0 #
b0 &
0$
0"
#195
b10011 !
b10011 '
1$
1"
b10010 #
b10010 &
#200
b0 !
b0 '
b10011 %
b0 #
b0 &
0$
0"
#205
b10100 !
b10100 '
1$
1"
b10011 #
b10011 &
#210
b0 !
b0 '
b10100 %
b0 #
b0 &
0$
0"
#215
b10101 !
b10101 '
1$
1"
b10100 #
b10100 &
#220
b0 !
b0 '
b10101 %
b0 #
b0 &
0$
0"
#225
b10110 !
b10110 '
1$
1"
b10101 #
b10101 &
#230
b0 !
b0 '
b10110 %
b0 #
b0 &
0$
0"
#235
b10111 !
b10111 '
1$
1"
b10110 #
b10110 &
#240
b0 !
b0 '
b10111 %
b0 #
b0 &
0$
0"
#245
b11000 !
b11000 '
1$
1"
b10111 #
b10111 &
#250
b0 !
b0 '
b11000 %
b0 #
b0 &
0$
0"
#255
b11001 !
b11001 '
1$
1"
b11000 #
b11000 &
#260
b0 !
b0 '
b11001 %
b0 #
b0 &
0$
0"
#265
b11010 !
b11010 '
1$
1"
b11001 #
b11001 &
#270
b0 !
b0 '
b11010 %
b0 #
b0 &
0$
0"
#275
b11011 !
b11011 '
1$
1"
b11010 #
b11010 &
#280
b0 !
b0 '
b11011 %
b0 #
b0 &
0$
0"
#285
b11100 !
b11100 '
1$
1"
b11011 #
b11011 &
#290
b0 !
b0 '
b11100 %
b0 #
b0 &
0$
0"
#295
b11101 !
b11101 '
1$
1"
b11100 #
b11100 &
#300
b0 !
b0 '
b11101 %
b0 #
b0 &
0$
0"
#305
b11110 !
b11110 '
1$
1"
b11101 #
b11101 &
#310
b0 !
b0 '
b11110 %
b0 #
b0 &
0$
0"
#315
b11111 !
b11111 '
1$
1"
b11110 #
b11110 &
#320
b0 !
b0 '
b11111 %
b0 #
b0 &
0$
0"
#325
b100000 !
b100000 '
1$
1"
b11111 #
b11111 &
#330
b0 !
b0 '
b100000 %
b0 #
b0 &
0$
0"
#335
b100001 !
b100001 '
1$
1"
b100000 #
b100000 &
#340
b0 !
b0 '
b100001 %
b0 #
b0 &
0$
0"
#345
b100010 !
b100010 '
1$
1"
b100001 #
b100001 &
#350
b0 !
b0 '
b100010 %
b0 #
b0 &
0$
0"
#355
b100011 !
b100011 '
1$
1"
b100010 #
b100010 &
#360
b0 !
b0 '
b100011 %
b0 #
b0 &
0$
0"
#365
b100100 !
b100100 '
1$
1"
b100011 #
b100011 &
#370
b0 !
b0 '
b100100 %
b0 #
b0 &
0$
0"
#375
b100101 !
b100101 '
1$
1"
b100100 #
b100100 &
#380
b0 !
b0 '
b100101 %
b0 #
b0 &
0$
0"
#385
b100110 !
b100110 '
1$
1"
b100101 #
b100101 &
#390
b0 !
b0 '
b100110 %
b0 #
b0 &
0$
0"
#395
b100111 !
b100111 '
1$
1"
b100110 #
b100110 &
#400
b0 !
b0 '
b100111 %
b0 #
b0 &
0$
0"
#405
b101000 !
b101000 '
1$
1"
b100111 #
b100111 &
#410
b0 !
b0 '
b101000 %
b0 #
b0 &
0$
0"
#415
b101001 !
b101001 '
1$
1"
b101000 #
b101000 &
#420
b0 !
b0 '
b101001 %
b0 #
b0 &
0$
0"
#425
b101010 !
b101010 '
1$
1"
b101001 #
b101001 &
#430
b0 !
b0 '
b101010 %
b0 #
b0 &
0$
0"
#435
b101011 !
b101011 '
1$
1"
b101010 #
b101010 &
#440
b0 !
b0 '
b101011 %
b0 #
b0 &
0$
0"
#445
b101100 !
b101100 '
1$
1"
b101011 #
b101011 &
#450
b0 !
b0 '
b101100 %
b0 #
b0 &
0$
0"
#455
b101101 !
b101101 '
1$
1"
b101100 #
b101100 &
#460
b0 !
b0 '
b101101 %
b0 #
b0 &
0$
0"
#465
b101110 !
b101110 '
1$
1"
b101101 #
b101101 &
#470
b0 !
b0 '
b101110 %
b0 #
b0 &
0$
0"
#475
b101111 !
b101111 '
1$
1"
b101110 #
b101110 &
#480
b0 !
b0 '
b101111 %
b0 #
b0 &
0$
0"
#485
b110000 !
b110000 '
1$
1"
b101111 #
b101111 &
#490
b0 !
b0 '
b110000 %
b0 #
b0 &
0$
0"
#495
b110001 !
b110001 '
1$
1"
b110000 #
b110000 &
#500
b0 !
b0 '
b110001 %
b0 #
b0 &
0$
0"
#505
b110010 !
b110010 '
1$
1"
b110001 #
b110001 &
#510
b0 !
b0 '
b110010 %
b0 #
b0 &
0$
0"
#515
b110011 !
b110011 '
1$
1"
b110010 #
b110010 &
#520
b0 !
b0 '
b110011 %
b0 #
b0 &
0$
0"
#525
b110100 !
b110100 '
1$
1"
b110011 #
b110011 &
#530
b0 !
b0 '
b110100 %
b0 #
b0 &
0$
0"
#535
b110101 !
b110101 '
1$
1"
b110100 #
b110100 &
#540
b0 !
b0 '
b110101 %
b0 #
b0 &
0$
0"
#545
b110110 !
b110110 '
1$
1"
b110101 #
b110101 &
#550
b0 !
b0 '
b110110 %
b0 #
b0 &
0$
0"
#555
b110111 !
b110111 '
1$
1"
b110110 #
b110110 &
#560
b0 !
b0 '
b110111 %
b0 #
b0 &
0$
0"
#565
b111000 !
b111000 '
1$
1"
b110111 #
b110111 &
#570
b0 !
b0 '
b111000 %
b0 #
b0 &
0$
0"
#575
b111001 !
b111001 '
1$
1"
b111000 #
b111000 &
#580
b0 !
b0 '
b111001 %
b0 #
b0 &
0$
0"
#585
b111010 !
b111010 '
1$
1"
b111001 #
b111001 &
#590
b0 !
b0 '
b111010 %
b0 #
b0 &
0$
0"
#595
b111011 !
b111011 '
1$
1"
b111010 #
b111010 &
#600
b0 !
b0 '
b111011 %
b0 #
b0 &
0$
0"
#605
b111100 !
b111100 '
1$
1"
b111011 #
b111011 &
#610
b0 !
b0 '
b111100 %
b0 #
b0 &
0$
0"
#615
b111101 !
b111101 '
1$
1"
b111100 #
b111100 &
#620
b0 !
b0 '
b111101 %
b0 #
b0 &
0$
0"
#625
b111110 !
b111110 '
1$
1"
b111101 #
b111101 &
#630
b0 !
b0 '
b111110 %
b0 #
b0 &
0$
0"
#635
b111111 !
b111111 '
1$
1"
b111110 #
b111110 &
#640
b0 !
b0 '
b111111 %
b0 #
b0 &
0$
0"
#645
b1000000 !
b1000000 '
1$
1"
b111111 #
b111111 &
#650
b0 !
b0 '
b1000000 %
b0 #
b0 &
0$
0"
#655
b1000001 !
b1000001 '
1$
1"
b1000000 #
b1000000 &
#660
b0 !
b0 '
b1000001 %
b0 #
b0 &
0$
0"
#665
b1000010 !
b1000010 '
1$
1"
b1000001 #
b1000001 &
#670
b0 !
b0 '
b1000010 %
b0 #
b0 &
0$
0"
#675
b1000011 !
b1000011 '
1$
1"
b1000010 #
b1000010 &
#680
b0 !
b0 '
b1000011 %
b0 #
b0 &
0$
0"
#685
b1000100 !
b1000100 '
1$
1"
b1000011 #
b1000011 &
#690
b0 !
b0 '
b1000100 %
b0 #
b0 &
0$
0"
#695
b1000101 !
b1000101 '
1$
1"
b1000100 #
b1000100 &
#700
b0 !
b0 '
b1000101 %
b0 #
b0 &
0$
0"
#705
b1000110 !
b1000110 '
1$
1"
b1000101 #
b1000101 &
#710
b0 !
b0 '
b1000110 %
b0 #
b0 &
0$
0"
#715
b1000111 !
b1000111 '
1$
1"
b1000110 #
b1000110 &
#720
b0 !
b0 '
b1000111 %
b0 #
b0 &
0$
0"
#725
b1001000 !
b1001000 '
1$
1"
b1000111 #
b1000111 &
#730
b0 !
b0 '
b1001000 %
b0 #
b0 &
0$
0"
#735
b1001001 !
b1001001 '
1$
1"
b1001000 #
b1001000 &
#740
b0 !
b0 '
b1001001 %
b0 #
b0 &
0$
0"
#745
b1001010 !
b1001010 '
1$
1"
b1001001 #
b1001001 &
#750
b0 !
b0 '
b1001010 %
b0 #
b0 &
0$
0"
#755
b1001011 !
b1001011 '
1$
1"
b1001010 #
b1001010 &
#760
b0 !
b0 '
b1001011 %
b0 #
b0 &
0$
0"
#765
b1001100 !
b1001100 '
1$
1"
b1001011 #
b1001011 &
#770
b0 !
b0 '
b1001100 %
b0 #
b0 &
0$
0"
#775
b1001101 !
b1001101 '
1$
1"
b1001100 #
b1001100 &
#780
b0 !
b0 '
b1001101 %
b0 #
b0 &
0$
0"
#785
b1001110 !
b1001110 '
1$
1"
b1001101 #
b1001101 &
#790
b0 !
b0 '
b1001110 %
b0 #
b0 &
0$
0"
#795
b1001111 !
b1001111 '
1$
1"
b1001110 #
b1001110 &
#800
b0 !
b0 '
b1001111 %
b0 #
b0 &
0$
0"
#805
b1010000 !
b1010000 '
1$
1"
b1001111 #
b1001111 &
#810
b0 !
b0 '
b1010000 %
b0 #
b0 &
0$
0"
#815
b1010001 !
b1010001 '
1$
1"
b1010000 #
b1010000 &
#820
b0 !
b0 '
b1010001 %
b0 #
b0 &
0$
0"
#825
b1010010 !
b1010010 '
1$
1"
b1010001 #
b1010001 &
#830
b0 !
b0 '
b1010010 %
b0 #
b0 &
0$
0"
#835
b1010011 !
b1010011 '
1$
1"
b1010010 #
b1010010 &
#840
b0 !
b0 '
b1010011 %
b0 #
b0 &
0$
0"
#845
b1010100 !
b1010100 '
1$
1"
b1010011 #
b1010011 &
#850
b0 !
b0 '
b1010100 %
b0 #
b0 &
0$
0"
#855
b1010101 !
b1010101 '
1$
1"
b1010100 #
b1010100 &
#860
b0 !
b0 '
b1010101 %
b0 #
b0 &
0$
0"
#865
b1010110 !
b1010110 '
1$
1"
b1010101 #
b1010101 &
#870
b0 !
b0 '
b1010110 %
b0 #
b0 &
0$
0"
#875
b1010111 !
b1010111 '
1$
1"
b1010110 #
b1010110 &
#880
b0 !
b0 '
b1010111 %
b0 #
b0 &
0$
0"
#885
b1011000 !
b1011000 '
1$
1"
b1010111 #
b1010111 &
#890
b0 !
b0 '
b1011000 %
b0 #
b0 &
0$
0"
#895
b1011001 !
b1011001 '
1$
1"
b1011000 #
b1011000 &
#900
b0 !
b0 '
b1011001 %
b0 #
b0 &
0$
0"
#905
b1011010 !
b1011010 '
1$
1"
b1011001 #
b1011001 &
#910
b0 !
b0 '
b1011010 %
b0 #
b0 &
0$
0"
#915
b1011011 !
b1011011 '
1$
1"
b1011010 #
b1011010 &
#920
b0 !
b0 '
b1011011 %
b0 #
b0 &
0$
0"
#925
b1011100 !
b1011100 '
1$
1"
b1011011 #
b1011011 &
#930
b0 !
b0 '
b1011100 %
b0 #
b0 &
0$
0"
#935
b1011101 !
b1011101 '
1$
1"
b1011100 #
b1011100 &
#940
b0 !
b0 '
b1011101 %
b0 #
b0 &
0$
0"
#945
b1011110 !
b1011110 '
1$
1"
b1011101 #
b1011101 &
#950
b0 !
b0 '
b1011110 %
b0 #
b0 &
0$
0"
#955
b1011111 !
b1011111 '
1$
1"
b1011110 #
b1011110 &
#960
b0 !
b0 '
b1011111 %
b0 #
b0 &
0$
0"
#965
b1100000 !
b1100000 '
1$
1"
b1011111 #
b1011111 &
#970
b0 !
b0 '
b1100000 %
b0 #
b0 &
0$
0"
#975
b1100001 !
b1100001 '
1$
1"
b1100000 #
b1100000 &
#980
b0 !
b0 '
b1100001 %
b0 #
b0 &
0$
0"
#985
b1100010 !
b1100010 '
1$
1"
b1100001 #
b1100001 &
#990
b0 !
b0 '
b1100010 %
b0 #
b0 &
0$
0"
#995
b1100011 !
b1100011 '
1$
1"
b1100010 #
b1100010 &
#1000
b0 !
b0 '
b1100011 %
b0 #
b0 &
0$
0"
#1005
b1100100 !
b1100100 '
1$
1"
b1100011 #
b1100011 &
#1010
b0 !
b0 '
b1100100 %
b0 #
b0 &
0$
0"
#1015
b1100101 !
b1100101 '
1$
1"
b1100100 #
b1100100 &
#1020
b0 !
b0 '
b1100101 %
b0 #
b0 &
0$
0"
#1025
b1100110 !
b1100110 '
1$
1"
b1100101 #
b1100101 &
#1030
b0 !
b0 '
b1100110 %
b0 #
b0 &
0$
0"
#1035
b1100111 !
b1100111 '
1$
1"
b1100110 #
b1100110 &
#1040
b0 !
b0 '
b1100111 %
b0 #
b0 &
0$
0"
#1045
b1101000 !
b1101000 '
1$
1"
b1100111 #
b1100111 &
#1050
b0 !
b0 '
b1101000 %
b0 #
b0 &
0$
0"
#1055
b1101001 !
b1101001 '
1$
1"
b1101000 #
b1101000 &
#1060
b0 !
b0 '
b1101001 %
b0 #
b0 &
0$
0"
#1065
b1101010 !
b1101010 '
1$
1"
b1101001 #
b1101001 &
#1070
b0 !
b0 '
b1101010 %
b0 #
b0 &
0$
0"
#1075
b1101011 !
b1101011 '
1$
1"
b1101010 #
b1101010 &
#1080
b0 !
b0 '
b1101011 %
b0 #
b0 &
0$
0"
#1085
b1101100 !
b1101100 '
1$
1"
b1101011 #
b1101011 &
#1090
b0 !
b0 '
b1101100 %
b0 #
b0 &
0$
0"
#1095
b1101101 !
b1101101 '
1$
1"
b1101100 #
b1101100 &
#1100
b0 !
b0 '
b1101101 %
b0 #
b0 &
0$
0"
#1105
b1101110 !
b1101110 '
1$
1"
b1101101 #
b1101101 &
#1110
b0 !
b0 '
b1101110 %
b0 #
b0 &
0$
0"
#1115
b1101111 !
b1101111 '
1$
1"
b1101110 #
b1101110 &
#1120
b0 !
b0 '
b1101111 %
b0 #
b0 &
0$
0"
#1125
b1110000 !
b1110000 '
1$
1"
b1101111 #
b1101111 &
#1130
b0 !
b0 '
b1110000 %
b0 #
b0 &
0$
0"
#1135
b1110001 !
b1110001 '
1$
1"
b1110000 #
b1110000 &
#1140
b0 !
b0 '
b1110001 %
b0 #
b0 &
0$
0"
#1145
b1110010 !
b1110010 '
1$
1"
b1110001 #
b1110001 &
#1150
b0 !
b0 '
b1110010 %
b0 #
b0 &
0$
0"
#1155
b1110011 !
b1110011 '
1$
1"
b1110010 #
b1110010 &
#1160
b0 !
b0 '
b1110011 %
b0 #
b0 &
0$
0"
#1165
b1110100 !
b1110100 '
1$
1"
b1110011 #
b1110011 &
#1170
b0 !
b0 '
b1110100 %
b0 #
b0 &
0$
0"
#1175
b1110101 !
b1110101 '
1$
1"
b1110100 #
b1110100 &
#1180
b0 !
b0 '
b1110101 %
b0 #
b0 &
0$
0"
#1185
b1110110 !
b1110110 '
1$
1"
b1110101 #
b1110101 &
#1190
b0 !
b0 '
b1110110 %
b0 #
b0 &
0$
0"
#1195
b1110111 !
b1110111 '
1$
1"
b1110110 #
b1110110 &
#1200
b0 !
b0 '
b1110111 %
b0 #
b0 &
0$
0"
#1205
b1111000 !
b1111000 '
1$
1"
b1110111 #
b1110111 &
#1210
b0 !
b0 '
b1111000 %
b0 #
b0 &
0$
0"
#1215
b1111001 !
b1111001 '
1$
1"
b1111000 #
b1111000 &
#1220
b0 !
b0 '
b1111001 %
b0 #
b0 &
0$
0"
#1225
b1111010 !
b1111010 '
1$
1"
b1111001 #
b1111001 &
#1230
b0 !
b0 '
b1111010 %
b0 #
b0 &
0$
0"
#1235
b1111011 !
b1111011 '
1$
1"
b1111010 #
b1111010 &
#1240
b0 !
b0 '
b1111011 %
b0 #
b0 &
0$
0"
#1245
b1111100 !
b1111100 '
1$
1"
b1111011 #
b1111011 &
#1250
b0 !
b0 '
b1111100 %
b0 #
b0 &
0$
0"
#1255
b1111101 !
b1111101 '
1$
1"
b1111100 #
b1111100 &
#1260
b0 !
b0 '
b1111101 %
b0 #
b0 &
0$
0"
#1265
b1111110 !
b1111110 '
1$
1"
b1111101 #
b1111101 &
#1270
b0 !
b0 '
b1111110 %
b0 #
b0 &
0$
0"
#1275
b1111111 !
b1111111 '
1$
1"
b1111110 #
b1111110 &
#1280
b0 !
b0 '
b1111111 %
b0 #
b0 &
0$
0"
#1285
b10000000 !
b10000000 '
1$
1"
b1111111 #
b1111111 &
#1290
b0 !
b0 '
b10000000 %
b0 #
b0 &
0$
0"
#1295
b10000001 !
b10000001 '
1$
1"
b10000000 #
b10000000 &
#1300
b0 !
b0 '
b10000001 %
b0 #
b0 &
0$
0"
#1305
b10000010 !
b10000010 '
1$
1"
b10000001 #
b10000001 &
#1310
b0 !
b0 '
b10000010 %
b0 #
b0 &
0$
0"
#1315
b10000011 !
b10000011 '
1$
1"
b10000010 #
b10000010 &
#1320
b0 !
b0 '
b10000011 %
b0 #
b0 &
0$
0"
#1325
b10000100 !
b10000100 '
1$
1"
b10000011 #
b10000011 &
#1330
b0 !
b0 '
b10000100 %
b0 #
b0 &
0$
0"
#1335
b10000101 !
b10000101 '
1$
1"
b10000100 #
b10000100 &
#1340
b0 !
b0 '
b10000101 %
b0 #
b0 &
0$
0"
#1345
b10000110 !
b10000110 '
1$
1"
b10000101 #
b10000101 &
#1350
b0 !
b0 '
b10000110 %
b0 #
b0 &
0$
0"
#1355
b10000111 !
b10000111 '
1$
1"
b10000110 #
b10000110 &
#1360
b0 !
b0 '
b10000111 %
b0 #
b0 &
0$
0"
#1365
b10001000 !
b10001000 '
1$
1"
b10000111 #
b10000111 &
#1370
b0 !
b0 '
b10001000 %
b0 #
b0 &
0$
0"
#1375
b10001001 !
b10001001 '
1$
1"
b10001000 #
b10001000 &
#1380
b0 !
b0 '
b10001001 %
b0 #
b0 &
0$
0"
#1385
b10001010 !
b10001010 '
1$
1"
b10001001 #
b10001001 &
#1390
b0 !
b0 '
b10001010 %
b0 #
b0 &
0$
0"
#1395
b10001011 !
b10001011 '
1$
1"
b10001010 #
b10001010 &
#1400
b0 !
b0 '
b10001011 %
b0 #
b0 &
0$
0"
#1405
b10001100 !
b10001100 '
1$
1"
b10001011 #
b10001011 &
#1410
b0 !
b0 '
b10001100 %
b0 #
b0 &
0$
0"
#1415
b10001101 !
b10001101 '
1$
1"
b10001100 #
b10001100 &
#1420
b0 !
b0 '
b10001101 %
b0 #
b0 &
0$
0"
#1425
b10001110 !
b10001110 '
1$
1"
b10001101 #
b10001101 &
#1430
b0 !
b0 '
b10001110 %
b0 #
b0 &
0$
0"
#1435
b10001111 !
b10001111 '
1$
1"
b10001110 #
b10001110 &
#1440
b0 !
b0 '
b10001111 %
b0 #
b0 &
0$
0"
#1445
b10010000 !
b10010000 '
1$
1"
b10001111 #
b10001111 &
#1450
b0 !
b0 '
b10010000 %
b0 #
b0 &
0$
0"
#1455
b10010001 !
b10010001 '
1$
1"
b10010000 #
b10010000 &
#1460
b0 !
b0 '
b10010001 %
b0 #
b0 &
0$
0"
#1465
b10010010 !
b10010010 '
1$
1"
b10010001 #
b10010001 &
#1470
b0 !
b0 '
b10010010 %
b0 #
b0 &
0$
0"
#1475
b10010011 !
b10010011 '
1$
1"
b10010010 #
b10010010 &
#1480
b0 !
b0 '
b10010011 %
b0 #
b0 &
0$
0"
#1485
b10010100 !
b10010100 '
1$
1"
b10010011 #
b10010011 &
#1490
b0 !
b0 '
b10010100 %
b0 #
b0 &
0$
0"
#1495
b10010101 !
b10010101 '
1$
1"
b10010100 #
b10010100 &
#1500
b0 !
b0 '
b10010101 %
b0 #
b0 &
0$
0"
#1505
b10010110 !
b10010110 '
1$
1"
b10010101 #
b10010101 &
#1510
b0 !
b0 '
b10010110 %
b0 #
b0 &
0$
0"
#1515
b10010111 !
b10010111 '
1$
1"
b10010110 #
b10010110 &
#1520
b0 !
b0 '
b10010111 %
b0 #
b0 &
0$
0"
#1525
b10011000 !
b10011000 '
1$
1"
b10010111 #
b10010111 &
#1530
b0 !
b0 '
b10011000 %
b0 #
b0 &
0$
0"
#1535
b10011001 !
b10011001 '
1$
1"
b10011000 #
b10011000 &
#1540
b0 !
b0 '
b10011001 %
b0 #
b0 &
0$
0"
#1545
b10011010 !
b10011010 '
1$
1"
b10011001 #
b10011001 &
#1550
b0 !
b0 '
b10011010 %
b0 #
b0 &
0$
0"
#1555
b10011011 !
b10011011 '
1$
1"
b10011010 #
b10011010 &
#1560
b0 !
b0 '
b10011011 %
b0 #
b0 &
0$
0"
#1565
b10011100 !
b10011100 '
1$
1"
b10011011 #
b10011011 &
#1570
b0 !
b0 '
b10011100 %
b0 #
b0 &
0$
0"
#1575
b10011101 !
b10011101 '
1$
1"
b10011100 #
b10011100 &
#1580
b0 !
b0 '
b10011101 %
b0 #
b0 &
0$
0"
#1585
b10011110 !
b10011110 '
1$
1"
b10011101 #
b10011101 &
#1590
b0 !
b0 '
b10011110 %
b0 #
b0 &
0$
0"
#1595
b10011111 !
b10011111 '
1$
1"
b10011110 #
b10011110 &
#1600
b0 !
b0 '
b10011111 %
b0 #
b0 &
0$
0"
#1605
b10100000 !
b10100000 '
1$
1"
b10011111 #
b10011111 &
#1610
b0 !
b0 '
b10100000 %
b0 #
b0 &
0$
0"
#1615
b10100001 !
b10100001 '
1$
1"
b10100000 #
b10100000 &
#1620
b0 !
b0 '
b10100001 %
b0 #
b0 &
0$
0"
#1625
b10100010 !
b10100010 '
1$
1"
b10100001 #
b10100001 &
#1630
b0 !
b0 '
b10100010 %
b0 #
b0 &
0$
0"
#1635
b10100011 !
b10100011 '
1$
1"
b10100010 #
b10100010 &
#1640
b0 !
b0 '
b10100011 %
b0 #
b0 &
0$
0"
#1645
b10100100 !
b10100100 '
1$
1"
b10100011 #
b10100011 &
#1650
b0 !
b0 '
b10100100 %
b0 #
b0 &
0$
0"
#1655
b10100101 !
b10100101 '
1$
1"
b10100100 #
b10100100 &
#1660
b0 !
b0 '
b10100101 %
b0 #
b0 &
0$
0"
#1665
b10100110 !
b10100110 '
1$
1"
b10100101 #
b10100101 &
#1670
b0 !
b0 '
b10100110 %
b0 #
b0 &
0$
0"
#1675
b10100111 !
b10100111 '
1$
1"
b10100110 #
b10100110 &
#1680
b0 !
b0 '
b10100111 %
b0 #
b0 &
0$
0"
#1685
b10101000 !
b10101000 '
1$
1"
b10100111 #
b10100111 &
#1690
b0 !
b0 '
b10101000 %
b0 #
b0 &
0$
0"
#1695
b10101001 !
b10101001 '
1$
1"
b10101000 #
b10101000 &
#1700
b0 !
b0 '
b10101001 %
b0 #
b0 &
0$
0"
#1705
b10101010 !
b10101010 '
1$
1"
b10101001 #
b10101001 &
#1710
b0 !
b0 '
b10101010 %
b0 #
b0 &
0$
0"
#1715
b10101011 !
b10101011 '
1$
1"
b10101010 #
b10101010 &
#1720
b0 !
b0 '
b10101011 %
b0 #
b0 &
0$
0"
#1725
b10101100 !
b10101100 '
1$
1"
b10101011 #
b10101011 &
#1730
b0 !
b0 '
b10101100 %
b0 #
b0 &
0$
0"
#1735
b10101101 !
b10101101 '
1$
1"
b10101100 #
b10101100 &
#1740
b0 !
b0 '
b10101101 %
b0 #
b0 &
0$
0"
#1745
b10101110 !
b10101110 '
1$
1"
b10101101 #
b10101101 &
#1750
b0 !
b0 '
b10101110 %
b0 #
b0 &
0$
0"
#1755
b10101111 !
b10101111 '
1$
1"
b10101110 #
b10101110 &
#1760
b0 !
b0 '
b10101111 %
b0 #
b0 &
0$
0"
#1765
b10110000 !
b10110000 '
1$
1"
b10101111 #
b10101111 &
#1770
b0 !
b0 '
b10110000 %
b0 #
b0 &
0$
0"
#1775
b10110001 !
b10110001 '
1$
1"
b10110000 #
b10110000 &
#1780
b0 !
b0 '
b10110001 %
b0 #
b0 &
0$
0"
#1785
b10110010 !
b10110010 '
1$
1"
b10110001 #
b10110001 &
#1790
b0 !
b0 '
b10110010 %
b0 #
b0 &
0$
0"
#1795
b10110011 !
b10110011 '
1$
1"
b10110010 #
b10110010 &
#1800
b0 !
b0 '
b10110011 %
b0 #
b0 &
0$
0"
#1805
b10110100 !
b10110100 '
1$
1"
b10110011 #
b10110011 &
#1810
b0 !
b0 '
b10110100 %
b0 #
b0 &
0$
0"
#1815
b10110101 !
b10110101 '
1$
1"
b10110100 #
b10110100 &
#1820
b0 !
b0 '
b10110101 %
b0 #
b0 &
0$
0"
#1825
b10110110 !
b10110110 '
1$
1"
b10110101 #
b10110101 &
#1830
b0 !
b0 '
b10110110 %
b0 #
b0 &
0$
0"
#1835
b10110111 !
b10110111 '
1$
1"
b10110110 #
b10110110 &
#1840
b0 !
b0 '
b10110111 %
b0 #
b0 &
0$
0"
#1845
b10111000 !
b10111000 '
1$
1"
b10110111 #
b10110111 &
#1850
b0 !
b0 '
b10111000 %
b0 #
b0 &
0$
0"
#1855
b10111001 !
b10111001 '
1$
1"
b10111000 #
b10111000 &
#1860
b0 !
b0 '
b10111001 %
b0 #
b0 &
0$
0"
#1865
b10111010 !
b10111010 '
1$
1"
b10111001 #
b10111001 &
#1870
b0 !
b0 '
b10111010 %
b0 #
b0 &
0$
0"
#1875
b10111011 !
b10111011 '
1$
1"
b10111010 #
b10111010 &
#1880
b0 !
b0 '
b10111011 %
b0 #
b0 &
0$
0"
#1885
b10111100 !
b10111100 '
1$
1"
b10111011 #
b10111011 &
#1890
b0 !
b0 '
b10111100 %
b0 #
b0 &
0$
0"
#1895
b10111101 !
b10111101 '
1$
1"
b10111100 #
b10111100 &
#1900
b0 !
b0 '
b10111101 %
b0 #
b0 &
0$
0"
#1905
b10111110 !
b10111110 '
1$
1"
b10111101 #
b10111101 &
#1910
b0 !
b0 '
b10111110 %
b0 #
b0 &
0$
0"
#1915
b10111111 !
b10111111 '
1$
1"
b10111110 #
b10111110 &
#1920
b0 !
b0 '
b10111111 %
b0 #
b0 &
0$
0"
#1925
b11000000 !
b11000000 '
1$
1"
b10111111 #
b10111111 &
#1930
b0 !
b0 '
b11000000 %
b0 #
b0 &
0$
0"
#1935
b11000001 !
b11000001 '
1$
1"
b11000000 #
b11000000 &
#1940
b0 !
b0 '
b11000001 %
b0 #
b0 &
0$
0"
#1945
b11000010 !
b11000010 '
1$
1"
b11000001 #
b11000001 &
#1950
b0 !
b0 '
b11000010 %
b0 #
b0 &
0$
0"
#1955
b11000011 !
b11000011 '
1$
1"
b11000010 #
b11000010 &
#1960
b0 !
b0 '
b11000011 %
b0 #
b0 &
0$
0"
#1965
b11000100 !
b11000100 '
1$
1"
b11000011 #
b11000011 &
#1970
b0 !
b0 '
b11000100 %
b0 #
b0 &
0$
0"
#1975
b11000101 !
b11000101 '
1$
1"
b11000100 #
b11000100 &
#1980
b0 !
b0 '
b11000101 %
b0 #
b0 &
0$
0"
